gns/__init__.py
gns/array_checks.py
gns/calculations.py
gns/geom.py
gns/geom_plots.py
gns/geom_sampler.py
gns/input.py
gns/keeton_calculations.py
gns/main.py
gns/mn_run.py
gns/nested_run.py
gns/nested_sampler.py
gns/ns_end_funcs.py
gns/ns_loop_funcs.py
gns/output.py
gns/plotting.py
gns/prob_funcs.py
gns/recurrence_calculations.py
gns/samplers.py
gns/setup_dicts.py
gns/theoretical_funcs.py
gns/tools.py
gns/toy_models.py
GNS-1.0.dist-info/LICENSE
GNS-1.0.dist-info/METADATA
GNS-1.0.dist-info/WHEEL
GNS-1.0.dist-info/top_level.txt
GNS-1.0.dist-info/RECORD
