Metadata-Version: 2.1
Name: GNS
Version: 1.0
Summary: Geometric nested sampling algorithm, as described in https://arxiv.org/abs/1905.09110.
Home-page: https://github.com/SuperKam91/gns
Author: Kamran Javid
Author-email: kj316@mrao.cam.ac.uk
License: MIT
Platform: UNKNOWN
Classifier: License :: OSI Approved :: MIT License
Classifier: Programming Language :: Python
Classifier: Programming Language :: Python :: 2.7
Requires-Python: >=2.7.0
Requires-Dist: numpy
Requires-Dist: scipy
Provides-Extra: multinest
Requires-Dist: pymultinest ; extra == 'multinest'
Provides-Extra: plotting
Requires-Dist: matplotlib ; extra == 'plotting'
Requires-Dist: getdist ; extra == 'plotting'
Requires-Dist: corner ; extra == 'plotting'
